wzy_dmpkg_two/__init__.py
wzy_dmpkg_two-0.0.2.dist-info/LICENSE
wzy_dmpkg_two-0.0.2.dist-info/METADATA
wzy_dmpkg_two-0.0.2.dist-info/WHEEL
wzy_dmpkg_two-0.0.2.dist-info/top_level.txt
wzy_dmpkg_two-0.0.2.dist-info/RECORD
