Metadata-Version: 2.1
Name: wzy_dmpkg_two
Version: 0.0.2
Summary: Any description you can put
Home-page: https://github.com/Dr-WangZhiyuan/wzy_dmpkg_two
Author: Dr. Zhiyuan Wang
Author-email: wang1399@e.ntu.edu.sg
License: MIT
Classifier: Programming Language :: Python :: 3
Classifier: License :: OSI Approved :: MIT License
License-File: LICENSE
Requires-Dist: numpy
